{
    "version": "5.6.0",
    "flags": {},
    "shapes": [
        {
            "label": "path",
            "points": [
                [
                    130.0,
                    181.0
                ],
                [
                    103.0,
                    208.0
                ],
                [
                    91.0,
                    201.0
                ],
                [
                    73.0,
                    187.0
                ],
                [
                    65.0,
                    186.0
                ],
                [
                    58.0,
                    191.0
                ],
                [
                    58.0,
                    202.0
                ],
                [
                    62.0,
                    206.0
                ],
                [
                    102.0,
                    233.0
                ],
                [
                    109.0,
                    232.0
                ],
                [
                    134.0,
                    206.0
                ],
                [
                    140.0,
                    208.0
                ],
                [
                    165.0,
                    231.0
                ],
                [
                    172.0,
                    232.0
                ],
                [
                    178.0,
                    228.0
                ],
                [
                    180.0,
                    220.0
                ],
                [
                    177.0,
                    214.0
                ],
                [
                    141.0,
                    181.0
                ]
            ],
            "group_id": null,
            "description": "",
            "shape_type": "polygon",
            "flags": {},
            "mask": null
        }
    ],
    "imagePath": "../images/1761137800.png",
    "imageData": null,
    "imageHeight": 262,
    "imageWidth": 197
}