{
    "version": "5.6.0",
    "flags": {},
    "shapes": [
        {
            "label": "path",
            "points": [
                [
                    86.0,
                    188.0
                ],
                [
                    81.0,
                    191.0
                ],
                [
                    43.0,
                    228.0
                ],
                [
                    43.0,
                    238.0
                ],
                [
                    48.0,
                    243.0
                ],
                [
                    55.0,
                    243.0
                ],
                [
                    59.0,
                    241.0
                ],
                [
                    89.0,
                    212.0
                ],
                [
                    97.0,
                    214.0
                ],
                [
                    127.0,
                    232.0
                ],
                [
                    133.0,
                    232.0
                ],
                [
                    139.0,
                    227.0
                ],
                [
                    140.0,
                    219.0
                ],
                [
                    135.0,
                    212.0
                ],
                [
                    92.0,
                    188.0
                ]
            ],
            "group_id": null,
            "description": "",
            "shape_type": "polygon",
            "flags": {},
            "mask": null
        }
    ],
    "imagePath": "../images/1766390006.png",
    "imageData": null,
    "imageHeight": 264,
    "imageWidth": 200
}