{
    "version": "5.6.0",
    "flags": {},
    "shapes": [
        {
            "label": "path",
            "points": [
                [
                    90.0,
                    130.0
                ],
                [
                    88.0,
                    131.0
                ],
                [
                    88.0,
                    140.0
                ],
                [
                    89.0,
                    143.0
                ],
                [
                    92.0,
                    145.0
                ],
                [
                    93.0,
                    150.0
                ],
                [
                    86.0,
                    154.0
                ],
                [
                    84.0,
                    157.0
                ],
                [
                    84.0,
                    235.0
                ],
                [
                    95.0,
                    241.0
                ],
                [
                    101.0,
                    242.0
                ],
                [
                    111.0,
                    252.0
                ],
                [
                    114.0,
                    253.0
                ],
                [
                    119.0,
                    251.0
                ],
                [
                    122.0,
                    247.0
                ],
                [
                    119.0,
                    235.0
                ],
                [
                    112.0,
                    229.0
                ],
                [
                    98.0,
                    224.0
                ],
                [
                    92.0,
                    218.0
                ],
                [
                    90.0,
                    213.0
                ],
                [
                    90.0,
                    197.0
                ],
                [
                    98.0,
                    171.0
                ],
                [
                    102.0,
                    166.0
                ],
                [
                    104.0,
                    166.0
                ],
                [
                    107.0,
                    163.0
                ],
                [
                    108.0,
                    155.0
                ],
                [
                    116.0,
                    147.0
                ],
                [
                    117.0,
                    133.0
                ],
                [
                    113.0,
                    130.0
                ],
                [
                    109.0,
                    132.0
                ],
                [
                    90.0,
                    130.0
                ],
                [
                    88.0,
                    113.0
                ],
                [
                    89.0,
                    111.0
                ],
                [
                    86.0,
                    110.0
                ],
                [
                    84.0,
                    106.0
                ],
                [
                    86.0,
                    102.0
                ],
                [
                    104.0,
                    95.0
                ],
                [
                    111.0,
                    101.0
                ],
                [
                    117.0,
                    101.0
                ],
                [
                    121.0,
                    103.0
                ],
                [
                    119.0,
                    100.0
                ],
                [
                    119.0,
                    92.0
                ],
                [
                    137.0,
                    88.0
                ],
                [
                    138.0,
                    91.0
                ],
                [
                    147.0,
                    99.0
                ],
                [
                    147.0,
                    108.0
                ],
                [
                    144.0,
                    113.0
                ],
                [
                    144.0,
                    117.0
                ],
                [
                    140.0,
                    122.0
                ],
                [
                    140.0,
                    134.0
                ],
                [
                    147.0,
                    142.0
                ],
                [
                    147.0,
                    158.0
                ],
                [
                    142.0,
                    175.0
                ],
                [
                    152.0,
                    195.0
                ],
                [
                    152.0,
                    207.0
                ],
                [
                    147.0,
                    219.0
                ],
                [
                    146.0,
                    228.0
                ],
                [
                    142.0,
                    234.0
                ],
                [
                    142.0,
                    239.0
                ],
                [
                    146.0,
                    243.0
                ],
                [
                    160.0,
                    241.0
                ],
                [
                    171.0,
                    246.0
                ],
                [
                    175.0,
                    242.0
                ],
                [
                    175.0,
                    239.0
                ],
                [
                    168.0,
                    217.0
                ],
                [
                    168.0,
                    205.0
                ],
                [
                    166.0,
                    202.0
                ],
                [
                    165.0,
                    191.0
                ],
                [
                    168.0,
                    181.0
                ],
                [
                    168.0,
                    171.0
                ],
                [
                    177.0,
                    158.0
                ],
                [
                    177.0,
                    149.0
                ],
                [
                    164.0,
                    135.0
                ],
                [
                    158.0,
                    121.0
                ],
                [
                    163.0,
                    107.0
                ],
                [
                    163.0,
                    91.0
                ],
                [
                    156.0,
                    78.0
                ],
                [
                    156.0,
                    75.0
                ],
                [
                    163.0,
                    64.0
                ],
                [
                    163.0,
                    47.0
                ],
                [
                    166.0,
                    40.0
                ],
                [
                    166.0,
                    35.0
                ],
                [
                    174.0,
                    27.0
                ],
                [
                    179.0,
                    27.0
                ],
                [
                    185.0,
                    24.0
                ],
                [
                    192.0,
                    24.0
                ],
                [
                    204.0,
                    29.0
                ],
                [
                    212.0,
                    29.0
                ],
                [
                    215.0,
                    27.0
                ],
                [
                    221.0,
                    27.0
                ],
                [
                    226.0,
                    24.0
                ],
                [
                    229.0,
                    24.0
                ],
                [
                    238.0,
                    33.0
                ],
                [
                    243.0,
                    48.0
                ],
                [
                    243.0,
                    54.0
                ],
                [
                    238.0,
                    71.0
                ],
                [
                    232.0,
                    80.0
                ],
                [
                    229.0,
                    80.0
                ],
                [
                    224.0,
                    76.0
                ],
                [
                    219.0,
                    59.0
                ],
                [
                    216.0,
                    55.0
                ],
                [
                    211.0,
                    52.0
                ],
                [
                    198.0,
                    49.0
                ],
                [
                    189.0,
                    52.0
                ],
                [
                    183.0,
                    60.0
                ],
                [
                    183.0,
                    76.0
                ],
                [
                    180.0,
                    82.0
                ],
                [
                    180.0,
                    104.0
                ],
                [
                    182.0,
                    107.0
                ],
                [
                    183.0,
                    117.0
                ],
                [
                    193.0,
                    134.0
                ],
                [
                    193.0,
                    140.0
                ],
                [
                    195.0,
                    143.0
                ],
                [
                    195.0,
                    149.0
                ],
                [
                    198.0,
                    157.0
                ],
                [
                    198.0,
                    168.0
                ],
                [
                    195.0,
                    173.0
                ],
                [
                    195.0,
                    180.0
                ],
                [
                    190.0,
                    196.0
                ],
                [
                    190.0,
                    208.0
                ],
                [
                    193.0,
                    214.0
                ],
                [
                    193.0,
                    227.0
                ],
                [
                    195.0,
                    230.0
                ],
                [
                    195.0,
                    251.0
                ],
                [
                    193.0,
                    254.0
                ],
                [
                    193.0,
                    263.0
                ],
                [
                    191.0,
                    267.0
                ],
                [
                    180.0,
                    275.0
                ],
                [
                    174.0,
                    278.0
                ],
                [
                    169.0,
                    278.0
                ],
                [
                    164.0,
                    281.0
                ],
                [
                    149.0,
                    281.0
                ],
                [
                    144.0,
                    278.0
                ],
                [
                    138.0,
                    278.0
                ],
                [
                    135.0,
                    276.0
                ],
                [
                    122.0,
                    276.0
                ],
                [
                    109.0,
                    281.0
                ],
                [
                    103.0,
                    281.0
                ],
                [
                    99.0,
                    279.0
                ],
                [
                    88.0,
                    267.0
                ],
                [
                    84.0,
                    265.0
                ],
                [
                    84.0,
                    288.0
                ],
                [
                    93.0,
                    294.0
                ],
                [
                    99.0,
                    294.0
                ],
                [
                    107.0,
                    297.0
                ],
                [
                    124.0,
                    296.0
                ],
                [
                    134.0,
                    292.0
                ],
                [
                    143.0,
                    296.0
                ],
                [
                    170.0,
                    296.0
                ],
                [
                    190.0,
                    291.0
                ],
                [
                    201.0,
                    282.0
                ],
                [
                    206.0,
                    272.0
                ],
                [
                    206.0,
                    267.0
                ],
                [
                    209.0,
                    261.0
                ],
                [
                    212.0,
                    246.0
                ],
                [
                    215.0,
                    241.0
                ],
                [
                    222.0,
                    234.0
                ],
                [
                    224.0,
                    234.0
                ],
                [
                    230.0,
                    237.0
                ],
                [
                    234.0,
                    242.0
                ],
                [
                    239.0,
                    254.0
                ],
                [
                    239.0,
                    261.0
                ],
                [
                    237.0,
                    266.0
                ],
                [
                    222.0,
                    280.0
                ],
                [
                    222.0,
                    286.0
                ],
                [
                    232.0,
                    294.0
                ],
                [
                    241.0,
                    294.0
                ],
                [
                    247.0,
                    292.0
                ],
                [
                    252.0,
                    296.0
                ],
                [
                    265.0,
                    296.0
                ],
                [
                    269.0,
                    294.0
                ],
                [
                    282.0,
                    293.0
                ],
                [
                    287.0,
                    289.0
                ],
                [
                    290.0,
                    284.0
                ],
                [
                    292.0,
                    264.0
                ],
                [
                    295.0,
                    256.0
                ],
                [
                    295.0,
                    234.0
                ],
                [
                    284.0,
                    222.0
                ],
                [
                    280.0,
                    221.0
                ],
                [
                    277.0,
                    218.0
                ],
                [
                    279.0,
                    216.0
                ],
                [
                    282.0,
                    216.0
                ],
                [
                    284.0,
                    213.0
                ],
                [
                    290.0,
                    212.0
                ],
                [
                    292.0,
                    209.0
                ],
                [
                    290.0,
                    205.0
                ],
                [
                    290.0,
                    194.0
                ],
                [
                    285.0,
                    184.0
                ],
                [
                    282.0,
                    181.0
                ],
                [
                    274.0,
                    180.0
                ],
                [
                    267.0,
                    185.0
                ],
                [
                    261.0,
                    184.0
                ],
                [
                    250.0,
                    191.0
                ],
                [
                    245.0,
                    200.0
                ],
                [
                    244.0,
                    214.0
                ],
                [
                    242.0,
                    219.0
                ],
                [
                    234.0,
                    226.0
                ],
                [
                    229.0,
                    226.0
                ],
                [
                    219.0,
                    222.0
                ],
                [
                    209.0,
                    214.0
                ],
                [
                    209.0,
                    210.0
                ],
                [
                    206.0,
                    205.0
                ],
                [
                    206.0,
                    194.0
                ],
                [
                    209.0,
                    189.0
                ],
                [
                    211.0,
                    167.0
                ],
                [
                    214.0,
                    161.0
                ],
                [
                    221.0,
                    155.0
                ],
                [
                    236.0,
                    151.0
                ],
                [
                    245.0,
                    152.0
                ],
                [
                    249.0,
                    154.0
                ],
                [
                    260.0,
                    154.0
                ],
                [
                    264.0,
                    157.0
                ],
                [
                    280.0,
                    159.0
                ],
                [
                    289.0,
                    152.0
                ],
                [
                    294.0,
                    140.0
                ],
                [
                    296.0,
                    125.0
                ],
                [
                    296.0,
                    118.0
                ],
                [
                    292.0,
                    107.0
                ],
                [
                    292.0,
                    100.0
                ],
                [
                    294.0,
                    96.0
                ],
                [
                    293.0,
                    79.0
                ],
                [
                    296.0,
                    69.0
                ],
                [
                    296.0,
                    48.0
                ],
                [
                    293.0,
                    42.0
                ],
                [
                    293.0,
                    28.0
                ],
                [
                    290.0,
                    23.0
                ],
                [
                    290.0,
                    18.0
                ],
                [
                    285.0,
                    11.0
                ],
                [
                    280.0,
                    11.0
                ],
                [
                    275.0,
                    16.0
                ],
                [
                    274.0,
                    20.0
                ],
                [
                    277.0,
                    36.0
                ],
                [
                    279.0,
                    38.0
                ],
                [
                    279.0,
                    49.0
                ],
                [
                    282.0,
                    55.0
                ],
                [
                    282.0,
                    61.0
                ],
                [
                    278.0,
                    73.0
                ],
                [
                    269.0,
                    80.0
                ],
                [
                    263.0,
                    81.0
                ],
                [
                    259.0,
                    79.0
                ],
                [
                    255.0,
                    72.0
                ],
                [
                    255.0,
                    64.0
                ],
                [
                    260.0,
                    50.0
                ],
                [
                    259.0,
                    37.0
                ],
                [
                    246.0,
                    15.0
                ],
                [
                    234.0,
                    8.0
                ],
                [
                    223.0,
                    8.0
                ],
                [
                    215.0,
                    13.0
                ],
                [
                    206.0,
                    13.0
                ],
                [
                    195.0,
                    8.0
                ],
                [
                    184.0,
                    8.0
                ],
                [
                    174.0,
                    13.0
                ],
                [
                    167.0,
                    13.0
                ],
                [
                    162.0,
                    10.0
                ],
                [
                    148.0,
                    13.0
                ],
                [
                    138.0,
                    8.0
                ],
                [
                    124.0,
                    8.0
                ],
                [
                    120.0,
                    11.0
                ],
                [
                    100.0,
                    13.0
                ],
                [
                    84.0,
                    23.0
                ],
                [
                    84.0,
                    50.0
                ],
                [
                    102.0,
                    35.0
                ],
                [
                    120.0,
                    25.0
                ],
                [
                    125.0,
                    24.0
                ],
                [
                    135.0,
                    28.0
                ],
                [
                    141.0,
                    34.0
                ],
                [
                    143.0,
                    43.0
                ],
                [
                    149.0,
                    55.0
                ],
                [
                    149.0,
                    62.0
                ],
                [
                    140.0,
                    76.0
                ],
                [
                    137.0,
                    88.0
                ],
                [
                    119.0,
                    92.0
                ],
                [
                    116.0,
                    84.0
                ],
                [
                    118.0,
                    77.0
                ],
                [
                    116.0,
                    75.0
                ],
                [
                    110.0,
                    74.0
                ],
                [
                    98.0,
                    68.0
                ],
                [
                    97.0,
                    74.0
                ],
                [
                    101.0,
                    81.0
                ],
                [
                    101.0,
                    86.0
                ],
                [
                    104.0,
                    95.0
                ],
                [
                    86.0,
                    102.0
                ],
                [
                    84.0,
                    99.0
                ],
                [
                    84.0,
                    113.0
                ],
                [
                    88.0,
                    113.0
                ]
            ],
            "group_id": null,
            "description": "",
            "shape_type": "polygon",
            "flags": {},
            "mask": null
        }
    ],
    "imagePath": "../images/1751167559.png",
    "imageData": null,
    "imageHeight": 301,
    "imageWidth": 304
}