{
    "version": "5.6.0",
    "flags": {},
    "shapes": [
        {
            "label": "path",
            "points": [
                [
                    54.0,
                    101.0
                ],
                [
                    53.0,
                    106.0
                ],
                [
                    69.0,
                    139.0
                ],
                [
                    67.0,
                    145.0
                ],
                [
                    60.0,
                    155.0
                ],
                [
                    60.0,
                    159.0
                ],
                [
                    68.0,
                    170.0
                ],
                [
                    69.0,
                    175.0
                ],
                [
                    59.0,
                    183.0
                ],
                [
                    43.0,
                    189.0
                ],
                [
                    36.0,
                    194.0
                ],
                [
                    36.0,
                    198.0
                ],
                [
                    41.0,
                    210.0
                ],
                [
                    41.0,
                    216.0
                ],
                [
                    35.0,
                    227.0
                ],
                [
                    36.0,
                    237.0
                ],
                [
                    40.0,
                    237.0
                ],
                [
                    43.0,
                    234.0
                ],
                [
                    52.0,
                    215.0
                ],
                [
                    48.0,
                    199.0
                ],
                [
                    64.0,
                    191.0
                ],
                [
                    78.0,
                    181.0
                ],
                [
                    82.0,
                    175.0
                ],
                [
                    71.0,
                    158.0
                ],
                [
                    72.0,
                    154.0
                ],
                [
                    80.0,
                    143.0
                ],
                [
                    80.0,
                    138.0
                ],
                [
                    71.0,
                    123.0
                ],
                [
                    64.0,
                    105.0
                ],
                [
                    61.0,
                    101.0
                ]
            ],
            "group_id": null,
            "description": "",
            "shape_type": "polygon",
            "flags": {},
            "mask": null
        }
    ],
    "imagePath": "../images/1750722611.png",
    "imageData": null,
    "imageHeight": 277,
    "imageWidth": 274
}