{
    "version": "5.6.0",
    "flags": {},
    "shapes": [
        {
            "label": "path",
            "points": [
                [
                    203.0,
                    39.0
                ],
                [
                    168.0,
                    65.0
                ],
                [
                    128.0,
                    104.0
                ],
                [
                    127.0,
                    112.0
                ],
                [
                    144.0,
                    139.0
                ],
                [
                    146.0,
                    147.0
                ],
                [
                    135.0,
                    171.0
                ],
                [
                    105.0,
                    197.0
                ],
                [
                    101.0,
                    198.0
                ],
                [
                    75.0,
                    187.0
                ],
                [
                    52.0,
                    154.0
                ],
                [
                    48.0,
                    152.0
                ],
                [
                    43.0,
                    152.0
                ],
                [
                    38.0,
                    156.0
                ],
                [
                    38.0,
                    167.0
                ],
                [
                    58.0,
                    197.0
                ],
                [
                    62.0,
                    201.0
                ],
                [
                    100.0,
                    218.0
                ],
                [
                    108.0,
                    218.0
                ],
                [
                    111.0,
                    216.0
                ],
                [
                    145.0,
                    188.0
                ],
                [
                    151.0,
                    181.0
                ],
                [
                    166.0,
                    148.0
                ],
                [
                    166.0,
                    140.0
                ],
                [
                    149.0,
                    113.0
                ],
                [
                    149.0,
                    109.0
                ],
                [
                    179.0,
                    80.0
                ],
                [
                    213.0,
                    54.0
                ],
                [
                    214.0,
                    44.0
                ],
                [
                    208.0,
                    39.0
                ]
            ],
            "group_id": null,
            "description": "",
            "shape_type": "polygon",
            "flags": {},
            "mask": null
        }
    ],
    "imagePath": "../images/1757117756.png",
    "imageData": null,
    "imageHeight": 246,
    "imageWidth": 247
}