{
    "version": "5.6.0",
    "flags": {},
    "shapes": [
        {
            "label": "path",
            "points": [
                [
                    113.0,
                    78.0
                ],
                [
                    108.0,
                    85.0
                ],
                [
                    109.0,
                    92.0
                ],
                [
                    113.0,
                    96.0
                ],
                [
                    142.0,
                    113.0
                ],
                [
                    149.0,
                    119.0
                ],
                [
                    157.0,
                    146.0
                ],
                [
                    156.0,
                    152.0
                ],
                [
                    128.0,
                    186.0
                ],
                [
                    94.0,
                    211.0
                ],
                [
                    85.0,
                    209.0
                ],
                [
                    65.0,
                    201.0
                ],
                [
                    56.0,
                    193.0
                ],
                [
                    45.0,
                    179.0
                ],
                [
                    44.0,
                    174.0
                ],
                [
                    70.0,
                    148.0
                ],
                [
                    74.0,
                    148.0
                ],
                [
                    96.0,
                    163.0
                ],
                [
                    106.0,
                    168.0
                ],
                [
                    114.0,
                    165.0
                ],
                [
                    117.0,
                    160.0
                ],
                [
                    117.0,
                    154.0
                ],
                [
                    111.0,
                    147.0
                ],
                [
                    72.0,
                    123.0
                ],
                [
                    67.0,
                    123.0
                ],
                [
                    63.0,
                    125.0
                ],
                [
                    20.0,
                    168.0
                ],
                [
                    20.0,
                    181.0
                ],
                [
                    48.0,
                    216.0
                ],
                [
                    92.0,
                    234.0
                ],
                [
                    97.0,
                    234.0
                ],
                [
                    101.0,
                    232.0
                ],
                [
                    144.0,
                    200.0
                ],
                [
                    176.0,
                    161.0
                ],
                [
                    180.0,
                    154.0
                ],
                [
                    179.0,
                    144.0
                ],
                [
                    177.0,
                    141.0
                ],
                [
                    167.0,
                    106.0
                ],
                [
                    161.0,
                    100.0
                ],
                [
                    124.0,
                    78.0
                ]
            ],
            "group_id": null,
            "description": "",
            "shape_type": "polygon",
            "flags": {},
            "mask": null
        }
    ],
    "imagePath": "../images/1751267188.png",
    "imageData": null,
    "imageHeight": 256,
    "imageWidth": 198
}