{
    "version": "5.6.0",
    "flags": {},
    "shapes": [
        {
            "label": "path",
            "points": [
                [
                    264.0,
                    36.0
                ],
                [
                    258.0,
                    44.0
                ],
                [
                    258.0,
                    53.0
                ],
                [
                    282.0,
                    89.0
                ],
                [
                    283.0,
                    93.0
                ],
                [
                    280.0,
                    97.0
                ],
                [
                    260.0,
                    111.0
                ],
                [
                    257.0,
                    111.0
                ],
                [
                    253.0,
                    108.0
                ],
                [
                    210.0,
                    67.0
                ],
                [
                    199.0,
                    66.0
                ],
                [
                    158.0,
                    86.0
                ],
                [
                    153.0,
                    88.0
                ],
                [
                    147.0,
                    88.0
                ],
                [
                    103.0,
                    51.0
                ],
                [
                    95.0,
                    48.0
                ],
                [
                    86.0,
                    51.0
                ],
                [
                    44.0,
                    97.0
                ],
                [
                    44.0,
                    118.0
                ],
                [
                    72.0,
                    164.0
                ],
                [
                    81.0,
                    172.0
                ],
                [
                    128.0,
                    188.0
                ],
                [
                    132.0,
                    194.0
                ],
                [
                    148.0,
                    237.0
                ],
                [
                    152.0,
                    243.0
                ],
                [
                    157.0,
                    246.0
                ],
                [
                    170.0,
                    245.0
                ],
                [
                    176.0,
                    238.0
                ],
                [
                    177.0,
                    230.0
                ],
                [
                    154.0,
                    172.0
                ],
                [
                    148.0,
                    165.0
                ],
                [
                    142.0,
                    162.0
                ],
                [
                    97.0,
                    147.0
                ],
                [
                    92.0,
                    142.0
                ],
                [
                    76.0,
                    116.0
                ],
                [
                    74.0,
                    112.0
                ],
                [
                    75.0,
                    105.0
                ],
                [
                    93.0,
                    85.0
                ],
                [
                    97.0,
                    84.0
                ],
                [
                    137.0,
                    117.0
                ],
                [
                    149.0,
                    121.0
                ],
                [
                    195.0,
                    99.0
                ],
                [
                    202.0,
                    98.0
                ],
                [
                    247.0,
                    141.0
                ],
                [
                    255.0,
                    145.0
                ],
                [
                    263.0,
                    144.0
                ],
                [
                    312.0,
                    109.0
                ],
                [
                    318.0,
                    101.0
                ],
                [
                    318.0,
                    92.0
                ],
                [
                    316.0,
                    88.0
                ],
                [
                    286.0,
                    44.0
                ],
                [
                    278.0,
                    36.0
                ]
            ],
            "group_id": null,
            "description": "",
            "shape_type": "polygon",
            "flags": {},
            "mask": null
        }
    ],
    "imagePath": "../images/1756688207.png",
    "imageData": null,
    "imageHeight": 366,
    "imageWidth": 366
}