{
    "version": "5.6.0",
    "flags": {},
    "shapes": [
        {
            "label": "path",
            "points": [
                [
                    109.0,
                    318.0
                ],
                [
                    105.0,
                    321.0
                ],
                [
                    100.0,
                    329.0
                ],
                [
                    100.0,
                    340.0
                ],
                [
                    102.0,
                    344.0
                ],
                [
                    156.0,
                    405.0
                ],
                [
                    173.0,
                    422.0
                ],
                [
                    180.0,
                    425.0
                ],
                [
                    191.0,
                    424.0
                ],
                [
                    246.0,
                    388.0
                ],
                [
                    255.0,
                    386.0
                ],
                [
                    311.0,
                    427.0
                ],
                [
                    334.0,
                    427.0
                ],
                [
                    340.0,
                    420.0
                ],
                [
                    340.0,
                    401.0
                ],
                [
                    334.0,
                    394.0
                ],
                [
                    268.0,
                    345.0
                ],
                [
                    257.0,
                    340.0
                ],
                [
                    246.0,
                    341.0
                ],
                [
                    188.0,
                    378.0
                ],
                [
                    181.0,
                    373.0
                ],
                [
                    132.0,
                    318.0
                ]
            ],
            "group_id": null,
            "description": "",
            "shape_type": "polygon",
            "flags": {},
            "mask": null
        }
    ],
    "imagePath": "../images/1757853171.png",
    "imageData": null,
    "imageHeight": 473,
    "imageWidth": 376
}