{
    "version": "5.6.0",
    "flags": {},
    "shapes": [
        {
            "label": "path",
            "points": [
                [
                    207.0,
                    36.0
                ],
                [
                    201.0,
                    42.0
                ],
                [
                    182.0,
                    80.0
                ],
                [
                    182.0,
                    88.0
                ],
                [
                    211.0,
                    126.0
                ],
                [
                    230.0,
                    137.0
                ],
                [
                    240.0,
                    145.0
                ],
                [
                    228.0,
                    168.0
                ],
                [
                    219.0,
                    175.0
                ],
                [
                    196.0,
                    186.0
                ],
                [
                    189.0,
                    180.0
                ],
                [
                    165.0,
                    152.0
                ],
                [
                    159.0,
                    149.0
                ],
                [
                    151.0,
                    151.0
                ],
                [
                    115.0,
                    181.0
                ],
                [
                    79.0,
                    207.0
                ],
                [
                    73.0,
                    213.0
                ],
                [
                    57.0,
                    254.0
                ],
                [
                    58.0,
                    265.0
                ],
                [
                    65.0,
                    269.0
                ],
                [
                    72.0,
                    268.0
                ],
                [
                    77.0,
                    262.0
                ],
                [
                    90.0,
                    226.0
                ],
                [
                    154.0,
                    175.0
                ],
                [
                    157.0,
                    175.0
                ],
                [
                    181.0,
                    202.0
                ],
                [
                    191.0,
                    210.0
                ],
                [
                    201.0,
                    208.0
                ],
                [
                    238.0,
                    188.0
                ],
                [
                    244.0,
                    182.0
                ],
                [
                    265.0,
                    145.0
                ],
                [
                    265.0,
                    138.0
                ],
                [
                    263.0,
                    134.0
                ],
                [
                    258.0,
                    130.0
                ],
                [
                    227.0,
                    112.0
                ],
                [
                    210.0,
                    92.0
                ],
                [
                    205.0,
                    84.0
                ],
                [
                    205.0,
                    81.0
                ],
                [
                    212.0,
                    66.0
                ],
                [
                    217.0,
                    60.0
                ],
                [
                    222.0,
                    61.0
                ],
                [
                    245.0,
                    72.0
                ],
                [
                    252.0,
                    73.0
                ],
                [
                    258.0,
                    69.0
                ],
                [
                    259.0,
                    59.0
                ],
                [
                    255.0,
                    54.0
                ],
                [
                    217.0,
                    36.0
                ]
            ],
            "group_id": null,
            "description": "",
            "shape_type": "polygon",
            "flags": {},
            "mask": null
        }
    ],
    "imagePath": "../images/1760524277.png",
    "imageData": null,
    "imageHeight": 317,
    "imageWidth": 317
}