{
    "version": "5.6.0",
    "flags": {},
    "shapes": [
        {
            "label": "path",
            "points": [
                [
                    121.0,
                    71.0
                ],
                [
                    80.0,
                    87.0
                ],
                [
                    42.0,
                    114.0
                ],
                [
                    35.0,
                    124.0
                ],
                [
                    17.0,
                    159.0
                ],
                [
                    17.0,
                    171.0
                ],
                [
                    35.0,
                    211.0
                ],
                [
                    44.0,
                    216.0
                ],
                [
                    80.0,
                    228.0
                ],
                [
                    88.0,
                    227.0
                ],
                [
                    92.0,
                    223.0
                ],
                [
                    93.0,
                    215.0
                ],
                [
                    91.0,
                    211.0
                ],
                [
                    82.0,
                    206.0
                ],
                [
                    52.0,
                    196.0
                ],
                [
                    48.0,
                    190.0
                ],
                [
                    38.0,
                    165.0
                ],
                [
                    57.0,
                    129.0
                ],
                [
                    87.0,
                    107.0
                ],
                [
                    124.0,
                    93.0
                ],
                [
                    142.0,
                    110.0
                ],
                [
                    145.0,
                    116.0
                ],
                [
                    124.0,
                    141.0
                ],
                [
                    86.0,
                    181.0
                ],
                [
                    85.0,
                    190.0
                ],
                [
                    88.0,
                    194.0
                ],
                [
                    91.0,
                    196.0
                ],
                [
                    99.0,
                    196.0
                ],
                [
                    104.0,
                    193.0
                ],
                [
                    141.0,
                    153.0
                ],
                [
                    170.0,
                    118.0
                ],
                [
                    170.0,
                    111.0
                ],
                [
                    166.0,
                    105.0
                ],
                [
                    132.0,
                    71.0
                ]
            ],
            "group_id": null,
            "description": "",
            "shape_type": "polygon",
            "flags": {},
            "mask": null
        }
    ],
    "imagePath": "../images/1761629560.png",
    "imageData": null,
    "imageHeight": 249,
    "imageWidth": 194
}