{
    "version": "5.6.0",
    "flags": {},
    "shapes": [
        {
            "label": "path",
            "points": [
                [
                    81.0,
                    215.0
                ],
                [
                    82.0,
                    212.0
                ],
                [
                    93.0,
                    212.0
                ],
                [
                    99.0,
                    206.0
                ],
                [
                    123.0,
                    190.0
                ],
                [
                    160.0,
                    157.0
                ],
                [
                    179.0,
                    119.0
                ],
                [
                    211.0,
                    86.0
                ],
                [
                    234.0,
                    48.0
                ],
                [
                    234.0,
                    41.0
                ],
                [
                    231.0,
                    37.0
                ],
                [
                    221.0,
                    37.0
                ],
                [
                    217.0,
                    41.0
                ],
                [
                    197.0,
                    74.0
                ],
                [
                    162.0,
                    111.0
                ],
                [
                    145.0,
                    146.0
                ],
                [
                    118.0,
                    171.0
                ],
                [
                    79.0,
                    199.0
                ],
                [
                    79.0,
                    209.0
                ],
                [
                    82.0,
                    212.0
                ]
            ],
            "group_id": null,
            "description": "",
            "shape_type": "polygon",
            "flags": {},
            "mask": null
        }
    ],
    "imagePath": "../images/1762131981.png",
    "imageData": null,
    "imageHeight": 284,
    "imageWidth": 281
}