{
    "version": "5.6.0",
    "flags": {},
    "shapes": [
        {
            "label": "path",
            "points": [
                [
                    140.0,
                    328.0
                ],
                [
                    65.0,
                    398.0
                ],
                [
                    65.0,
                    419.0
                ],
                [
                    70.0,
                    425.0
                ],
                [
                    76.0,
                    428.0
                ],
                [
                    88.0,
                    428.0
                ],
                [
                    94.0,
                    425.0
                ],
                [
                    164.0,
                    361.0
                ],
                [
                    170.0,
                    350.0
                ],
                [
                    170.0,
                    341.0
                ],
                [
                    167.0,
                    335.0
                ],
                [
                    159.0,
                    328.0
                ]
            ],
            "group_id": null,
            "description": "",
            "shape_type": "polygon",
            "flags": {},
            "mask": null
        }
    ],
    "imagePath": "../images/1756564002.png",
    "imageData": null,
    "imageHeight": 476,
    "imageWidth": 371
}